[
  {
    "writerName": "নুসরাত জাহান লিজা",
    "writerSlug": "a001-nusrat-jahan-liza",
    "writerImage": "https://res.cloudinary.com/dhj4ovvav/image/upload/w_600,q_auto,f_auto/v1768226843/authorLiza_tcncxq.webp",
    "writerBio": "পারিবারিক, রঙ্গ, রস মিশ্রিত গল্পের দক্ষ লেখিকা"
  },
  {
    "writerName": "অভ্রায়ীনি ঐশি",
    "writerSlug": "a002-avrayini-oishi",
    "writerImage": "https://res.cloudinary.com/dhj4ovvav/image/upload/v1778255111/avra_q4y9pn.webp",
    "writerBio": "রোমান্টিক ও থ্রিলার ভিত্তিক গল্প লেখিকা"
  },
  {
    "writerName": "মোঃ সাইফুল ইসলাম",
    "writerSlug": "a003-saiful-islam",
    "writerImage": "https://res.cloudinary.com/dhj4ovvav/image/upload/v1776407787/saiful-islam_n6vqoq.webp",
    "writerBio": "বাংলা সামাজিক ও রোমান্টিক গল্প লেখক"
  },
  {
    "writerName": "মৌরিন আহমেদ",
    "writerSlug": "a004-mourin",
    "writerImage": "https://res.cloudinary.com/dhj4ovvav/image/upload/w_600,q_auto,f_auto/v1768291297/mourin-ahmed_bkugjb.webp",
    "writerBio": "নারী-জীবন ও সামাজিক প্রেক্ষাপটের গল্প লেখেন"
  },
  {
    "writerName": "মহুয়া আমরিন বিন্দু",
    "writerSlug": "a005-mohuya-amrin",
    "writerImage": "https://res.cloudinary.com/dhj4ovvav/image/upload/v1773567220/641429218_122184272030478576_5338759348626111994_n_u2fdlf.jpg",
    "writerBio": "চমৎকার লেখনীতে পারদর্শী লেখিকা"
  },
  {
    "writerName": "নবনীতা চৌধুরী",
    "writerSlug": "a006-navnita-chowdhury",
    "writerImage": "https://res.cloudinary.com/dhj4ovvav/image/upload/v1772229166/navs_dbsfmj.webp",
    "writerBio": "বাংলা রোমান্টিক ও পারিবারিক গল্প লেখিকা"
  },
  {
    "writerName": "নওরিন ইথিকা",
    "writerSlug": "a007-noureen",
    "writerImage": "https://res.cloudinary.com/dhj4ovvav/image/upload/v1772632860/888i_azpmry.webp",
    "writerBio": "বাংলা সামাজিক ও রোমান্টিক গল্প লেখিকা"
  },
  {
    "writerName": "তিয়াশা চৌধুরী",
    "writerSlug": "a008-tiyasha",
    "writerImage": "https://res.cloudinary.com/dhj4ovvav/image/upload/v1772980008/ok_axgljf.webp",
    "writerBio": "বাংলা গ্রামীন ও সামাজিক গল্প লেখিকা"
  },
  {
    "writerName": "অয়ন্তিকা রাফিয়াত ঐশী",
    "writerSlug": "a009-oyontika-rafiath",
    "writerImage": "https://res.cloudinary.com/dhj4ovvav/image/upload/v1773184956/oyontika_ipvgev.jpg",
    "writerBio": "পারিবারিক ও সামাজিক গল্পে পারদর্শী লেখিকা"
  },
  {
    "writerName": "বৃষ্টি শেখ",
    "writerSlug": "a010-bristy-sheikh",
    "writerImage": "https://res.cloudinary.com/dhj4ovvav/image/upload/v1780243940/bristy_fuv43v.webp",
    "writerBio": "রোমান্টিক, সাসপেন্স ও থ্রিলার ভিত্তিক গল্প লেখিকা"
  },
  {
    "writerName": "বন্যা সিকদার",
    "writerSlug": "a011-bonna-sikder",
    "writerImage": "https://res.cloudinary.com/dhj4ovvav/image/upload/v1780112806/bonna-s-1_dqn31s.webp",
    "writerBio": "রোমান্টিক ও সামাজিক গল্প লেখিকা"
  },
  {
    "writerName": "খুশবু আকতার",
    "writerSlug": "a012-khusbu-akter",
    "writerImage": "https://res.cloudinary.com/dhj4ovvav/image/upload/v1780409196/Krushuyta1_vsoym9.webp",
    "writerBio": "সামাজিক, রোমান্টিক এবং থ্রিলার গল্প লেখিকা"
  },
  {
    "writerName": "জান্নাতী আক্তার সিমি",
    "writerSlug": "a013-jannati-akter-simi",
    "writerImage": "https://res.cloudinary.com/dhj4ovvav/image/upload/v1780235856/jannati2_qrp11m.webp",
    "writerBio": "রোমান্স ও থ্রিলারভিত্তিক গল্প লেখিকা"
  },
  {
    "writerName": "আজেরিন হিরানুর",
    "writerSlug": "a014-azerin-hiranur",
    "writerImage": "https://res.cloudinary.com/dhj4ovvav/image/upload/v1780889944/azerin_dmsbm2.webp",
    "writerBio": "বাংলা রোমান্টিক গল্প লেখিকা"
  },
  {
    "writerName": "সূচনা জাফরিন",
    "writerSlug": "a015-suchana-jafrin",
    "writerImage": "https://res.cloudinary.com/didbcg0dd/image/upload/q_auto/f_auto/v1781089637/suchana-jafrin_yqa5ro.webp",
    "writerBio": "প্রেম, বিচ্ছেদ ও সামাজিক গল্প লেখিকা"
  }
]